nautobot_sfp_inventory/__init__.py
nautobot_sfp_inventory/api/__init__.py
nautobot_sfp_inventory/api/filters.py
nautobot_sfp_inventory/api/serializers.py
nautobot_sfp_inventory/api/urls.py
nautobot_sfp_inventory/api/views.py
nautobot_sfp_inventory/filters.py
nautobot_sfp_inventory/forms.py
nautobot_sfp_inventory/migrations/0001_initial.py
nautobot_sfp_inventory/migrations/0002_sfp_assigned_device.py
nautobot_sfp_inventory/migrations/0003_auto_20220419_1309.py
nautobot_sfp_inventory/migrations/0004_sfp_assigned.py
nautobot_sfp_inventory/migrations/0005_auto_20220420_1230.py
nautobot_sfp_inventory/migrations/0006_sfptype_comments.py
nautobot_sfp_inventory/migrations/0007_sfp_procurement_ident.py
nautobot_sfp_inventory/migrations/0008_auto_20240221_1339.py
nautobot_sfp_inventory/migrations/__init__.py
nautobot_sfp_inventory/models.py
nautobot_sfp_inventory/navigation.py
nautobot_sfp_inventory/tables.py
nautobot_sfp_inventory/template_content.py
nautobot_sfp_inventory/templates/nautobot_sfp_inventory/inc/assigned_sfps.html
nautobot_sfp_inventory/templates/nautobot_sfp_inventory/inc/sfp_add_header.html
nautobot_sfp_inventory/templates/nautobot_sfp_inventory/sfp.html
nautobot_sfp_inventory/templates/nautobot_sfp_inventory/sfp_add.html
nautobot_sfp_inventory/templates/nautobot_sfp_inventory/sfp_bulk_add.html
nautobot_sfp_inventory/templates/nautobot_sfp_inventory/sfptype.html
nautobot_sfp_inventory/test_sfp.csv
nautobot_sfp_inventory/test_types.csv
nautobot_sfp_inventory/urls.py
nautobot_sfp_inventory/views.py
nautobot_sfp_inventory-1.1.3.dist-info/LICENSE.txt
nautobot_sfp_inventory-1.1.3.dist-info/METADATA
nautobot_sfp_inventory-1.1.3.dist-info/WHEEL
nautobot_sfp_inventory-1.1.3.dist-info/RECORD
