Metadata-Version: 2.1
Name: nautobot-sfp-inventory
Version: 1.1.3
Summary: A Nautobot plugin for SFP inventory management
Home-page: https://gitlab-ce.gwdg.de/gwdg-netz/nautobot-plugins/nautobot-sfp-inventory
License: Apache-2.0
Author: Gesellschaft für wissenschaftliche Datenverarbeitung mbH Göttingen
Requires-Python: >=3.11,<3.12
Classifier: License :: OSI Approved :: Apache Software License
Classifier: Programming Language :: Python :: 3
Classifier: Programming Language :: Python :: 3.11
Requires-Dist: nautobot (>=2.0.0,<3.0.0)
Project-URL: Repository, https://gitlab-ce.gwdg.de/gwdg-netz/nautobot-plugins/nautobot-sfp-inventory
